planvantage/__init__.py
planvantage/auth.py
planvantage/client.py
planvantage/exceptions.py
planvantage/http.py
planvantage/py.typed
planvantage/utils.py
planvantage/models/__init__.py
planvantage/models/aimodel.py
planvantage/models/apikey.py
planvantage/models/base.py
planvantage/models/census.py
planvantage/models/contribution.py
planvantage/models/plandesign.py
planvantage/models/plandocument.py
planvantage/models/plansponsor.py
planvantage/models/rateplan.py
planvantage/models/scenario.py
planvantage/models/user.py
planvantage/resources/__init__.py
planvantage/resources/aimodels.py
planvantage/resources/apikeys.py
planvantage/resources/base.py
planvantage/resources/benchmarks.py
planvantage/resources/census.py
planvantage/resources/contributions.py
planvantage/resources/export.py
planvantage/resources/plandesigns.py
planvantage/resources/plandocuments.py
planvantage/resources/plansponsors.py
planvantage/resources/rateplans.py
planvantage/resources/scenarios.py
planvantage/resources/settings.py
planvantage-0.2.0.dist-info/licenses/LICENSE
planvantage-0.2.0.dist-info/METADATA
planvantage-0.2.0.dist-info/WHEEL
planvantage-0.2.0.dist-info/top_level.txt
planvantage-0.2.0.dist-info/RECORD
